aparnik/__init__.py
aparnik/apps.py
aparnik/celery.py
aparnik/clock.py
aparnik/routing.py
aparnik/settings.py
aparnik/views.py
aparnik/api/__init__.py
aparnik/api/serializers.py
aparnik/contrib/__init__.py
aparnik/contrib/aboutus/__init__.py
aparnik/contrib/aboutus/admin.py
aparnik/contrib/aboutus/apps.py
aparnik/contrib/aboutus/models.py
aparnik/contrib/aboutus/tests.py
aparnik/contrib/aboutus/views.py
aparnik/contrib/aboutus/api/__init__.py
aparnik/contrib/aboutus/api/serializers.py
aparnik/contrib/aboutus/api/urls.py
aparnik/contrib/aboutus/api/views.py
aparnik/contrib/aboutus/migrations/0001_initial.py
aparnik/contrib/aboutus/migrations/0002_auto_20200107_1403.py
aparnik/contrib/aboutus/migrations/0003_auto_20200405_1627.py
aparnik/contrib/aboutus/migrations/0004_auto_20200405_1628.py
aparnik/contrib/aboutus/migrations/0005_auto_20200411_1226.py
aparnik/contrib/aboutus/migrations/__init__.py
aparnik/contrib/aboutus/static/css/location_picker.css
aparnik/contrib/aboutus/static/js/jquery.location_picker.js
aparnik/contrib/addresses/__init__.py
aparnik/contrib/addresses/admin.py
aparnik/contrib/addresses/apps.py
aparnik/contrib/addresses/models.py
aparnik/contrib/addresses/api/__init__.py
aparnik/contrib/addresses/api/serializers.py
aparnik/contrib/addresses/api/urls.py
aparnik/contrib/addresses/api/views.py
aparnik/contrib/addresses/migrations/0001_initial.py
aparnik/contrib/addresses/migrations/__init__.py
aparnik/contrib/audits/__init__.py
aparnik/contrib/audits/admin.py
aparnik/contrib/audits/apps.py
aparnik/contrib/audits/models.py
aparnik/contrib/audits/api/__init__.py
aparnik/contrib/audits/api/urls.py
aparnik/contrib/audits/api/admin/__init__.py
aparnik/contrib/audits/api/admin/serializers.py
aparnik/contrib/audits/api/admin/urls.py
aparnik/contrib/audits/api/admin/views.py
aparnik/contrib/audits/migrations/0001_initial.py
aparnik/contrib/audits/migrations/__init__.py
aparnik/contrib/bankaccounts/__init__.py
aparnik/contrib/bankaccounts/admin.py
django_apar-2.0.15.dist-info/LICENSE
django_apar-2.0.15.dist-info/METADATA
django_apar-2.0.15.dist-info/WHEEL
django_apar-2.0.15.dist-info/top_level.txt
django_apar-2.0.15.dist-info/RECORD
