Metadata-Version: 2.1
Name: django-apar
Version: 2.0.15
Summary: Aparnik is a simple Django app to help about some common problems.
Home-page: https://www.aparnik.com/
Author: Ali Zahedi Gol
Author-email: zahedi@aparnik.com
License: BSD License
Platform: UNKNOWN
Classifier: Environment :: Web Environment
Classifier: Framework :: Django
Classifier: Framework :: Django :: 2.2
Classifier: Intended Audience :: Developers
Classifier: License :: OSI Approved :: BSD License
Classifier: Operating System :: OS Independent
Classifier: Programming Language :: Python
Classifier: Programming Language :: Python :: 3.7
Classifier: Topic :: Internet :: WWW/HTTP
Classifier: Topic :: Internet :: WWW/HTTP :: Dynamic Content
License-File: LICENSE
Requires-Dist: boto3
Requires-Dist: humanize
Requires-Dist: django (==2.2)
Requires-Dist: django-polymorphic
Requires-Dist: django-rest-polymorphic
Requires-Dist: pycryptodome (>=3.9.7)
Requires-Dist: django-s3direct
Requires-Dist: djangorestframework
Requires-Dist: python-dateutil
Requires-Dist: kavenegar
Requires-Dist: django-jalali-date
Requires-Dist: Pillow
Requires-Dist: fcm-django
Requires-Dist: zeep
Requires-Dist: django-dynamic-raw-id
Requires-Dist: APScheduler
Requires-Dist: django-filter (==2.1.0)
Requires-Dist: django-ckeditor
Requires-Dist: django-tagulous
Requires-Dist: django-colorfield
Requires-Dist: Faker
Requires-Dist: python-magic
Requires-Dist: PyPDF2 (==1.26.0)
Requires-Dist: django-enumfield (==1.5)
Requires-Dist: redis (==3.2.0)
Requires-Dist: channels (==2.4.0)
Requires-Dist: channels-redis (==2.4.1)
Requires-Dist: celery (==4.4.0)
Requires-Dist: django-admin-rangefilter (==0.5.3)
Requires-Dist: django-import-export (==2.0.1)
Requires-Dist: uvicorn (==0.11.1)
Requires-Dist: az-iranian-bank-gateways (==1.6.15)
